SJRSdetects/DetectaFormas.py
SJRSdetects/DetectaMovCamara.py
SJRSdetects/DetectaMovFotos.py
SJRSdetects/DetectaMovVideo.py
SJRSdetects/TestDetectaMovCamara.py
SJRSdetects/__init__.py
SJRSdetects-1.0.6.dist-info/METADATA
SJRSdetects-1.0.6.dist-info/WHEEL
SJRSdetects-1.0.6.dist-info/top_level.txt
SJRSdetects-1.0.6.dist-info/RECORD
